[
    {
        "title": "Nvidia tumbles 19% after missing on revenue and guidance",
        "publish_date": "11/16/2018",
        "vader_score_raw": {
            "neg": 0.216,
            "neu": 0.784,
            "pos": 0.0,
            "compound": -0.296
        },
        "vader_score_lemmatized": {
            "neg": 0.216,
            "neu": 0.784,
            "pos": 0.0,
            "compound": -0.296
        },
        "vader_score_steemed": {
            "neg": 0.167,
            "neu": 0.833,
            "pos": 0.0,
            "compound": -0.1531
        },
        "vader_score_stopwords": {
            "neg": 0.306,
            "neu": 0.694,
            "pos": 0.0,
            "compound": -0.296
        },
        "stock_ratio": {
            "-7": -0.028096512945689527,
            "-5": -0.08670512979836847,
            "-3": -0.029197101634643334,
            "0": -0.15647269752950008,
            "3": -0.22277713470899596,
            "5": -0.1571296539948587,
            "7": -0.1154684533633816
        }
    },
    {
        "title": "NVIDIA adds 'Control' and other games to GeForce Now",
        "publish_date": "03/27/2020",
        "vader_score_raw": {
            "neg": 0.0,
            "neu": 1.0,
            "pos": 0.0,
            "compound": 0.0
        },
        "vader_score_lemmatized": {
            "neg": 0.0,
            "neu": 1.0,
            "pos": 0.0,
            "compound": 0.0
        },
        "vader_score_steemed": {
            "neg": 0.0,
            "neu": 1.0,
            "pos": 0.0,
            "compound": 0.0
        },
        "vader_score_stopwords": {
            "neg": 0.0,
            "neu": 1.0,
            "pos": 0.0,
            "compound": 0.0
        },
        "stock_ratio": {
            "-7": -0.03491774643560675,
            "-5": 6.053285321639624e-05,
            "-3": 0.16510809364694035,
            "0": 0.08124401989349395,
            "3": 0.10085854021306039,
            "5": -0.042509132152909565,
            "7": -0.041670093872223465
        }
    },
    {
        "title": "Exclusive: Nvidia offers new advanced chip for China that meets U.S. export controls",
        "publish_date": "11/07/2022",
        "vader_score_raw": {
            "neg": 0.0,
            "neu": 0.759,
            "pos": 0.241,
            "compound": 0.3612
        },
        "vader_score_lemmatized": {
            "neg": 0.0,
            "neu": 0.759,
            "pos": 0.241,
            "compound": 0.3612
        },
        "vader_score_steemed": {
            "neg": 0.0,
            "neu": 0.889,
            "pos": 0.111,
            "compound": 0.128
        },
        "vader_score_stopwords": {
            "neg": 0.0,
            "neu": 0.72,
            "pos": 0.28,
            "compound": 0.3612
        },
        "stock_ratio": {
            "-7": 0.02997965079793535,
            "-5": -0.009558273316677487,
            "-3": 0.044767264410269854,
            "0": 0.04309630275869035,
            "3": 0.11111104272278235,
            "5": 0.08419598651287583,
            "7": 0.08419598651287583
        }
    },
    {
        "title": "Nvidia says it is working with Microsoft to build 'massive' cloud AI computer",
        "publish_date": "11/16/2022",
        "vader_score_raw": {
            "neg": 0.0,
            "neu": 1.0,
            "pos": 0.0,
            "compound": 0.0
        },
        "vader_score_lemmatized": {
            "neg": 0.0,
            "neu": 1.0,
            "pos": 0.0,
            "compound": 0.0
        },
        "vader_score_steemed": {
            "neg": 0.0,
            "neu": 1.0,
            "pos": 0.0,
            "compound": 0.0
        },
        "vader_score_stopwords": {
            "neg": 0.0,
            "neu": 1.0,
            "pos": 0.0,
            "compound": 0.0
        },
        "stock_ratio": {
            "-7": -0.006040097161518626,
            "-5": 0.11683424852843663,
            "-3": 0.08419598651287583,
            "0": 0.01869637588165187,
            "3": -0.03926488043368406,
            "5": -0.03926488043368406,
            "7": 0.03673254074324973
        }
    },
    {
        "title": "Nvidia third-quarter revenue up on strong data center demand",
        "publish_date": "11/16/2022",
        "vader_score_raw": {
            "neg": 0.127,
            "neu": 0.593,
            "pos": 0.28,
            "compound": 0.4215
        },
        "vader_score_lemmatized": {
            "neg": 0.127,
            "neu": 0.593,
            "pos": 0.28,
            "compound": 0.4215
        },
        "vader_score_steemed": {
            "neg": 0.127,
            "neu": 0.593,
            "pos": 0.28,
            "compound": 0.4215
        },
        "vader_score_stopwords": {
            "neg": 0.153,
            "neu": 0.51,
            "pos": 0.337,
            "compound": 0.4215
        },
        "stock_ratio": {
            "-7": -0.006040097161518626,
            "-5": 0.11683424852843663,
            "-3": 0.08419598651287583,
            "0": 0.01869637588165187,
            "3": -0.03926488043368406,
            "5": -0.03926488043368406,
            "7": 0.03673254074324973
        }
    },
    {
        "title": "Nvidia earnings: Revenue beats expectations, bottom line falls short",
        "publish_date": "11/16/2022",
        "vader_score_raw": {
            "neg": 0.0,
            "neu": 1.0,
            "pos": 0.0,
            "compound": 0.0
        },
        "vader_score_lemmatized": {
            "neg": 0.0,
            "neu": 1.0,
            "pos": 0.0,
            "compound": 0.0
        },
        "vader_score_steemed": {
            "neg": 0.0,
            "neu": 1.0,
            "pos": 0.0,
            "compound": 0.0
        },
        "vader_score_stopwords": {
            "neg": 0.0,
            "neu": 1.0,
            "pos": 0.0,
            "compound": 0.0
        },
        "stock_ratio": {
            "-7": -0.006040097161518626,
            "-5": 0.11683424852843663,
            "-3": 0.08419598651287583,
            "0": 0.01869637588165187,
            "3": -0.03926488043368406,
            "5": -0.03926488043368406,
            "7": 0.03673254074324973
        }
    },
    {
        "title": "Should You Invest in NVIDIA Corporation (NVDA)?",
        "publish_date": "11/02/2022",
        "vader_score_raw": {
            "neg": 0.0,
            "neu": 1.0,
            "pos": 0.0,
            "compound": 0.0
        },
        "vader_score_lemmatized": {
            "neg": 0.0,
            "neu": 1.0,
            "pos": 0.0,
            "compound": 0.0
        },
        "vader_score_steemed": {
            "neg": 0.0,
            "neu": 1.0,
            "pos": 0.0,
            "compound": 0.0
        },
        "vader_score_stopwords": {
            "neg": 0.0,
            "neu": 1.0,
            "pos": 0.0,
            "compound": 0.0
        },
        "stock_ratio": {
            "-7": 0.032458747548937204,
            "-5": 0.07090880913481708,
            "-3": 0.02997965079793535,
            "0": -0.009558273316677487,
            "3": 0.04309630275869035,
            "5": 0.04309630275869035,
            "7": -0.006040097161518626
        }
    },
    {
        "title": "Nvidia (NVDA) Gains As Market Dips: What You Should Know",
        "publish_date": "11/01/2022",
        "vader_score_raw": {
            "neg": 0.0,
            "neu": 0.789,
            "pos": 0.211,
            "compound": 0.34
        },
        "vader_score_lemmatized": {
            "neg": 0.0,
            "neu": 0.789,
            "pos": 0.211,
            "compound": 0.34
        },
        "vader_score_steemed": {
            "neg": 0.0,
            "neu": 0.726,
            "pos": 0.274,
            "compound": 0.5267
        },
        "vader_score_stopwords": {
            "neg": 0.0,
            "neu": 0.676,
            "pos": 0.324,
            "compound": 0.34
        },
        "stock_ratio": {
            "-7": 0.07406331638737106,
            "-5": 0.04048827263499836,
            "-3": 0.02997965079793535,
            "0": 0.021496472107206815,
            "3": 0.044767264410269854,
            "5": 0.04309630275869035,
            "7": 0.05659555432014814
        }
    },
    {
        "title": "Nvidia\u2019s Rebound Hides Tough Reality for Chipmakers",
        "publish_date": "11/15/2022",
        "vader_score_raw": {
            "neg": 0.39,
            "neu": 0.61,
            "pos": 0.0,
            "compound": -0.296
        },
        "vader_score_lemmatized": {
            "neg": 0.39,
            "neu": 0.61,
            "pos": 0.0,
            "compound": -0.296
        },
        "vader_score_steemed": {
            "neg": 0.39,
            "neu": 0.61,
            "pos": 0.0,
            "compound": -0.296
        },
        "vader_score_stopwords": {
            "neg": 0.444,
            "neu": 0.556,
            "pos": 0.0,
            "compound": -0.296
        },
        "stock_ratio": {
            "-7": 0.05659555432014814,
            "-5": 0.11111104272278235,
            "-3": 0.08419598651287583,
            "0": 0.08304164884662862,
            "3": -0.03722988394842472,
            "5": -0.03926488043368406,
            "7": 0.008570446194936389
        }
    },
    {
        "title": "Here's Why NVIDIA (NASDAQ:NVDA) Has Caught The Eye Of Investors",
        "publish_date": "10/29/2022",
        "vader_score_raw": {
            "neg": 0.0,
            "neu": 1.0,
            "pos": 0.0,
            "compound": 0.0
        },
        "vader_score_lemmatized": {
            "neg": 0.0,
            "neu": 1.0,
            "pos": 0.0,
            "compound": 0.0
        },
        "vader_score_steemed": {
            "neg": 0.0,
            "neu": 0.789,
            "pos": 0.211,
            "compound": 0.34
        },
        "vader_score_stopwords": {
            "neg": 0.0,
            "neu": 1.0,
            "pos": 0.0,
            "compound": 0.0
        },
        "stock_ratio": {
            "-7": 0.04503978518971865,
            "-5": 0.04503978518971865,
            "-3": 0.032458747548937204,
            "0": 0.02997965079793535,
            "3": 0.021496472107206815,
            "5": 0.003857506818130168,
            "7": 0.04309630275869035
        }
    },
    {
        "title": "Nvidia Is Affordable for the First Time in Years",
        "publish_date": "11/07/2022",
        "vader_score_raw": {
            "neg": 0.0,
            "neu": 1.0,
            "pos": 0.0,
            "compound": 0.0
        },
        "vader_score_lemmatized": {
            "neg": 0.0,
            "neu": 1.0,
            "pos": 0.0,
            "compound": 0.0
        },
        "vader_score_steemed": {
            "neg": 0.0,
            "neu": 1.0,
            "pos": 0.0,
            "compound": 0.0
        },
        "vader_score_stopwords": {
            "neg": 0.0,
            "neu": 1.0,
            "pos": 0.0,
            "compound": 0.0
        },
        "stock_ratio": {
            "-7": 0.02997965079793535,
            "-5": -0.009558273316677487,
            "-3": 0.044767264410269854,
            "0": 0.04309630275869035,
            "3": 0.11111104272278235,
            "5": 0.08419598651287583,
            "7": 0.08419598651287583
        }
    },
    {
        "title": "Nvidia Sales Beat Estimates as Data-Center Business Fuels Growth",
        "publish_date": "11/06/2022",
        "vader_score_raw": {
            "neg": 0.0,
            "neu": 0.755,
            "pos": 0.245,
            "compound": 0.3818
        },
        "vader_score_lemmatized": {
            "neg": 0.0,
            "neu": 0.755,
            "pos": 0.245,
            "compound": 0.3818
        },
        "vader_score_steemed": {
            "neg": 0.0,
            "neu": 0.755,
            "pos": 0.245,
            "compound": 0.3818
        },
        "vader_score_stopwords": {
            "neg": 0.0,
            "neu": 0.729,
            "pos": 0.271,
            "compound": 0.3818
        },
        "stock_ratio": {
            "-7": 0.02997965079793535,
            "-5": 0.021496472107206815,
            "-3": 0.003857506818130168,
            "0": 0.04309630275869035,
            "3": -0.006040097161518626,
            "5": 0.11683424852843663,
            "7": 0.08419598651287583
        }
    },
    {
        "title": "Will NVIDIA Corporation (NVDA) Bounce Back?",
        "publish_date": "11/08/2022",
        "vader_score_raw": {
            "neg": 0.0,
            "neu": 1.0,
            "pos": 0.0,
            "compound": 0.0
        },
        "vader_score_lemmatized": {
            "neg": 0.0,
            "neu": 1.0,
            "pos": 0.0,
            "compound": 0.0
        },
        "vader_score_steemed": {
            "neg": 0.0,
            "neu": 1.0,
            "pos": 0.0,
            "compound": 0.0
        },
        "vader_score_stopwords": {
            "neg": 0.0,
            "neu": 1.0,
            "pos": 0.0,
            "compound": 0.0
        },
        "stock_ratio": {
            "-7": 0.021496472107206815,
            "-5": 0.003857506818130168,
            "-3": 0.04309630275869035,
            "0": 0.05659555432014814,
            "3": 0.11683424852843663,
            "5": 0.08419598651287583,
            "7": 0.08304164884662862
        }
    },
    {
        "title": "Explainer: Why are Nvidia's shares soaring and what is its role in the AI boom?",
        "publish_date": "06/14/2023",
        "vader_score_raw": {
            "neg": 0.0,
            "neu": 0.864,
            "pos": 0.136,
            "compound": 0.296
        },
        "vader_score_lemmatized": {
            "neg": 0.0,
            "neu": 0.864,
            "pos": 0.136,
            "compound": 0.296
        },
        "vader_score_steemed": {
            "neg": 0.0,
            "neu": 0.864,
            "pos": 0.136,
            "compound": 0.296
        },
        "vader_score_stopwords": {
            "neg": 0.0,
            "neu": 0.732,
            "pos": 0.268,
            "compound": 0.296
        },
        "stock_ratio": {
            "-7": -0.03669503879447849,
            "-5": -0.0009966580447969345,
            "-3": 0.018413932958852602,
            "0": 0.0869355951291695,
            "3": 0.052267468621981186,
            "5": 0.052267468621981186,
            "7": 0.018992293139857012
        }
    },
    {
        "title": "Nvidia shares soar nearly 30% as sales forecast jumps and AI booms",
        "publish_date": "05/24/2023",
        "vader_score_raw": {
            "neg": 0.0,
            "neu": 0.833,
            "pos": 0.167,
            "compound": 0.296
        },
        "vader_score_lemmatized": {
            "neg": 0.0,
            "neu": 0.833,
            "pos": 0.167,
            "compound": 0.296
        },
        "vader_score_steemed": {
            "neg": 0.0,
            "neu": 0.833,
            "pos": 0.167,
            "compound": 0.296
        },
        "vader_score_stopwords": {
            "neg": 0.0,
            "neu": 0.804,
            "pos": 0.196,
            "compound": 0.296
        },
        "stock_ratio": {
            "-7": 0.04206835607216456,
            "-5": 0.05112295474513735,
            "-3": 0.035246402822800345,
            "0": -0.004512497148062339,
            "3": 0.1664872555096856,
            "5": 0.1664872555096856,
            "7": 0.07103484180576251
        }
    },
    {
        "title": "Why Nvidia is suddenly one of the most valuable companies in the world",
        "publish_date": "05/25/2023",
        "vader_score_raw": {
            "neg": 0.0,
            "neu": 0.78,
            "pos": 0.22,
            "compound": 0.5256
        },
        "vader_score_lemmatized": {
            "neg": 0.0,
            "neu": 0.78,
            "pos": 0.22,
            "compound": 0.5256
        },
        "vader_score_steemed": {
            "neg": 0.0,
            "neu": 1.0,
            "pos": 0.0,
            "compound": 0.0
        },
        "vader_score_stopwords": {
            "neg": 0.0,
            "neu": 0.617,
            "pos": 0.383,
            "compound": 0.4767
        },
        "stock_ratio": {
            "-7": 0.07735210727135826,
            "-5": 0.035246402822800345,
            "-3": 0.035246402822800345,
            "0": 0.18951946960981553,
            "3": 0.1664872555096856,
            "5": 0.1664872555096856,
            "7": 0.08802630782663767
        }
    },
    {
        "title": "Chip giant Nvidia nears trillion-dollar status on AI bet",
        "publish_date": "05/25/2023",
        "vader_score_raw": {
            "neg": 0.0,
            "neu": 1.0,
            "pos": 0.0,
            "compound": 0.0
        },
        "vader_score_lemmatized": {
            "neg": 0.0,
            "neu": 1.0,
            "pos": 0.0,
            "compound": 0.0
        },
        "vader_score_steemed": {
            "neg": 0.0,
            "neu": 1.0,
            "pos": 0.0,
            "compound": 0.0
        },
        "vader_score_stopwords": {
            "neg": 0.0,
            "neu": 1.0,
            "pos": 0.0,
            "compound": 0.0
        },
        "stock_ratio": {
            "-7": 0.07735210727135826,
            "-5": 0.035246402822800345,
            "-3": 0.035246402822800345,
            "0": 0.18951946960981553,
            "3": 0.1664872555096856,
            "5": 0.1664872555096856,
            "7": 0.08802630782663767
        }
    },
    {
        "title": "Nvidia joins tech titans in trillion-dollar club",
        "publish_date": "05/30/2023",
        "vader_score_raw": {
            "neg": 0.0,
            "neu": 1.0,
            "pos": 0.0,
            "compound": 0.0
        },
        "vader_score_lemmatized": {
            "neg": 0.0,
            "neu": 0.732,
            "pos": 0.268,
            "compound": 0.296
        },
        "vader_score_steemed": {
            "neg": 0.0,
            "neu": 0.732,
            "pos": 0.268,
            "compound": 0.296
        },
        "vader_score_stopwords": {
            "neg": 0.0,
            "neu": 1.0,
            "pos": 0.0,
            "compound": 0.0
        },
        "stock_ratio": {
            "-7": 0.007816056973525066,
            "-5": 0.18951946960981553,
            "-3": 0.1664872555096856,
            "0": 0.1664872555096856,
            "3": 0.0407665978757061,
            "5": 0.003873496721046212,
            "7": -0.011814623643783622
        }
    },
    {
        "title": "Nvidia Nailed Bet on AI Trend in Surge Toward $1 Trillion",
        "publish_date": "05/26/2023",
        "vader_score_raw": {
            "neg": 0.0,
            "neu": 1.0,
            "pos": 0.0,
            "compound": 0.0
        },
        "vader_score_lemmatized": {
            "neg": 0.0,
            "neu": 1.0,
            "pos": 0.0,
            "compound": 0.0
        },
        "vader_score_steemed": {
            "neg": 0.0,
            "neu": 1.0,
            "pos": 0.0,
            "compound": 0.0
        },
        "vader_score_stopwords": {
            "neg": 0.0,
            "neu": 1.0,
            "pos": 0.0,
            "compound": 0.0
        },
        "stock_ratio": {
            "-7": 0.05112295474513735,
            "-5": 0.035246402822800345,
            "-3": 0.007816056973525066,
            "0": 0.1737287815970571,
            "3": 0.1664872555096856,
            "5": 0.07103484180576251,
            "7": 0.0407665978757061
        }
    },
    {
        "title": "Nvidia stock explodes after 'guidance for the ages': What Wall Street is saying",
        "publish_date": "05/25/2023",
        "vader_score_raw": {
            "neg": 0.0,
            "neu": 1.0,
            "pos": 0.0,
            "compound": 0.0
        },
        "vader_score_lemmatized": {
            "neg": 0.0,
            "neu": 1.0,
            "pos": 0.0,
            "compound": 0.0
        },
        "vader_score_steemed": {
            "neg": 0.0,
            "neu": 1.0,
            "pos": 0.0,
            "compound": 0.0
        },
        "vader_score_stopwords": {
            "neg": 0.0,
            "neu": 1.0,
            "pos": 0.0,
            "compound": 0.0
        },
        "stock_ratio": {
            "-7": 0.07735210727135826,
            "-5": 0.035246402822800345,
            "-3": 0.035246402822800345,
            "0": 0.18951946960981553,
            "3": 0.1664872555096856,
            "5": 0.1664872555096856,
            "7": 0.08802630782663767
        }
    },
    {
        "title": "If You Invested $1000 in Nvidia a Decade Ago, This is How Much It'd Be Worth Now",
        "publish_date": "05/24/2023",
        "vader_score_raw": {
            "neg": 0.0,
            "neu": 0.894,
            "pos": 0.106,
            "compound": 0.2263
        },
        "vader_score_lemmatized": {
            "neg": 0.0,
            "neu": 0.894,
            "pos": 0.106,
            "compound": 0.2263
        },
        "vader_score_steemed": {
            "neg": 0.0,
            "neu": 0.894,
            "pos": 0.106,
            "compound": 0.2263
        },
        "vader_score_stopwords": {
            "neg": 0.0,
            "neu": 0.787,
            "pos": 0.213,
            "compound": 0.2263
        },
        "stock_ratio": {
            "-7": 0.04206835607216456,
            "-5": 0.05112295474513735,
            "-3": 0.035246402822800345,
            "0": -0.004512497148062339,
            "3": 0.1664872555096856,
            "5": 0.1664872555096856,
            "7": 0.07103484180576251
        }
    },
    {
        "title": "There\u2019s an AI war, and Nvidia is the only arms dealer: Analyst",
        "publish_date": "05/25/2023",
        "vader_score_raw": {
            "neg": 0.262,
            "neu": 0.738,
            "pos": 0.0,
            "compound": -0.5994
        },
        "vader_score_lemmatized": {
            "neg": 0.262,
            "neu": 0.738,
            "pos": 0.0,
            "compound": -0.5994
        },
        "vader_score_steemed": {
            "neg": 0.262,
            "neu": 0.738,
            "pos": 0.0,
            "compound": -0.5994
        },
        "vader_score_stopwords": {
            "neg": 0.394,
            "neu": 0.606,
            "pos": 0.0,
            "compound": -0.5994
        },
        "stock_ratio": {
            "-7": 0.07735210727135826,
            "-5": 0.035246402822800345,
            "-3": 0.035246402822800345,
            "0": 0.18951946960981553,
            "3": 0.1664872555096856,
            "5": 0.1664872555096856,
            "7": 0.08802630782663767
        }
    },
    {
        "title": "Investors who showed Q1 bets on Nvidia may have got boost as it joined $1 trillion club",
        "publish_date": "05/30/2023",
        "vader_score_raw": {
            "neg": 0.0,
            "neu": 0.856,
            "pos": 0.144,
            "compound": 0.4019
        },
        "vader_score_lemmatized": {
            "neg": 0.0,
            "neu": 0.856,
            "pos": 0.144,
            "compound": 0.4019
        },
        "vader_score_steemed": {
            "neg": 0.0,
            "neu": 0.754,
            "pos": 0.246,
            "compound": 0.5994
        },
        "vader_score_stopwords": {
            "neg": 0.0,
            "neu": 0.803,
            "pos": 0.197,
            "compound": 0.4019
        },
        "stock_ratio": {
            "-7": 0.007816056973525066,
            "-5": 0.18951946960981553,
            "-3": 0.1664872555096856,
            "0": 0.1664872555096856,
            "3": 0.0407665978757061,
            "5": 0.003873496721046212,
            "7": -0.011814623643783622
        }
    },
    {
        "title": "Nvidia is not the only firm cashing in on the AI gold rush",
        "publish_date": "05/29/2023",
        "vader_score_raw": {
            "neg": 0.0,
            "neu": 1.0,
            "pos": 0.0,
            "compound": 0.0
        },
        "vader_score_lemmatized": {
            "neg": 0.0,
            "neu": 1.0,
            "pos": 0.0,
            "compound": 0.0
        },
        "vader_score_steemed": {
            "neg": 0.0,
            "neu": 1.0,
            "pos": 0.0,
            "compound": 0.0
        },
        "vader_score_stopwords": {
            "neg": 0.0,
            "neu": 1.0,
            "pos": 0.0,
            "compound": 0.0
        },
        "stock_ratio": {
            "-7": 0.035246402822800345,
            "-5": -0.004512497148062339,
            "-3": 0.1737287815970571,
            "0": 0.1664872555096856,
            "3": 0.08802630782663767,
            "5": 0.003873496721046212,
            "7": 0.003873496721046212
        }
    },
    {
        "title": "Nvidia CEO: \u2018We don\u2019t have any magic bullets\u2019 to deal with chip shortage",
        "publish_date": "11/10/2021",
        "vader_score_raw": {
            "neg": 0.143,
            "neu": 0.857,
            "pos": 0.0,
            "compound": -0.25
        },
        "vader_score_lemmatized": {
            "neg": 0.143,
            "neu": 0.857,
            "pos": 0.0,
            "compound": -0.25
        },
        "vader_score_steemed": {
            "neg": 0.0,
            "neu": 1.0,
            "pos": 0.0,
            "compound": 0.0
        },
        "vader_score_stopwords": {
            "neg": 0.2,
            "neu": 0.8,
            "pos": 0.0,
            "compound": -0.25
        },
        "stock_ratio": {
            "-7": 0.043047072516937436,
            "-5": 0.10258510151789411,
            "-3": 0.10720419435929855,
            "0": 0.013471038025234645,
            "3": -0.006156711737484063,
            "5": -0.006156711737484063,
            "7": -0.02641840486398721
        }
    },
    {
        "title": "Nvidia expects first-quarter sales to exceed $5.3 bln",
        "publish_date": "04/12/2021",
        "vader_score_raw": {
            "neg": 0.0,
            "neu": 1.0,
            "pos": 0.0,
            "compound": 0.0
        },
        "vader_score_lemmatized": {
            "neg": 0.0,
            "neu": 1.0,
            "pos": 0.0,
            "compound": 0.0
        },
        "vader_score_steemed": {
            "neg": 0.0,
            "neu": 1.0,
            "pos": 0.0,
            "compound": 0.0
        },
        "vader_score_stopwords": {
            "neg": 0.0,
            "neu": 1.0,
            "pos": 0.0,
            "compound": 0.0
        },
        "stock_ratio": {
            "-7": 0.06032473731886425,
            "-5": 0.042454405904187364,
            "-3": 0.02994297024107233,
            "0": 0.06750942965078457,
            "3": 0.07414670575753284,
            "5": -0.004118906286684859,
            "7": -0.004118906286684859
        }
    },
    {
        "title": "Nvidia is on top of the world, but its rivals are gaining steam",
        "publish_date": "11/10/2021",
        "vader_score_raw": {
            "neg": 0.0,
            "neu": 0.683,
            "pos": 0.317,
            "compound": 0.6249
        },
        "vader_score_lemmatized": {
            "neg": 0.0,
            "neu": 0.683,
            "pos": 0.317,
            "compound": 0.6249
        },
        "vader_score_steemed": {
            "neg": 0.0,
            "neu": 0.647,
            "pos": 0.353,
            "compound": 0.7184
        },
        "vader_score_stopwords": {
            "neg": 0.0,
            "neu": 0.465,
            "pos": 0.535,
            "compound": 0.5574
        },
        "stock_ratio": {
            "-7": 0.043047072516937436,
            "-5": 0.10258510151789411,
            "-3": 0.10720419435929855,
            "0": 0.013471038025234645,
            "3": -0.006156711737484063,
            "5": -0.006156711737484063,
            "7": -0.02641840486398721
        }
    },
    {
        "title": "U.S. near deal for Nvidia supercomputer as it waits for delayed Intel machine -sources",
        "publish_date": "08/24/2021",
        "vader_score_raw": {
            "neg": 0.128,
            "neu": 0.872,
            "pos": 0.0,
            "compound": -0.2263
        },
        "vader_score_lemmatized": {
            "neg": 0.128,
            "neu": 0.872,
            "pos": 0.0,
            "compound": -0.2263
        },
        "vader_score_steemed": {
            "neg": 0.15,
            "neu": 0.85,
            "pos": 0.0,
            "compound": -0.3182
        },
        "vader_score_stopwords": {
            "neg": 0.174,
            "neu": 0.826,
            "pos": 0.0,
            "compound": -0.2263
        },
        "stock_ratio": {
            "-7": -0.02312978519650611,
            "-5": 0.003969943050749654,
            "-3": 0.0885076381674779,
            "0": 0.06818702394885161,
            "3": 0.04739496182039327,
            "5": 0.030122258502887772,
            "7": 0.006277452865868662
        }
    },
    {
        "title": "Nvidia launches new products to plug cars, factories into its Omniverse",
        "publish_date": "11/09/2021",
        "vader_score_raw": {
            "neg": 0.0,
            "neu": 1.0,
            "pos": 0.0,
            "compound": 0.0
        },
        "vader_score_lemmatized": {
            "neg": 0.0,
            "neu": 1.0,
            "pos": 0.0,
            "compound": 0.0
        },
        "vader_score_steemed": {
            "neg": 0.0,
            "neu": 1.0,
            "pos": 0.0,
            "compound": 0.0
        },
        "vader_score_stopwords": {
            "neg": 0.0,
            "neu": 1.0,
            "pos": 0.0,
            "compound": 0.0
        },
        "stock_ratio": {
            "-7": 0.0556178822638278,
            "-5": 0.1362904570216241,
            "-3": 0.10720419435929855,
            "0": 0.07385415408532073,
            "3": 0.006991658784402685,
            "5": -0.006156711737484063,
            "7": -0.0023924053182937605
        }
    },
    {
        "title": "Nvidia metaverse future bright even as Arm may slip from grasp",
        "publish_date": "12/03/2021",
        "vader_score_raw": {
            "neg": 0.0,
            "neu": 0.775,
            "pos": 0.225,
            "compound": 0.4404
        },
        "vader_score_lemmatized": {
            "neg": 0.0,
            "neu": 0.775,
            "pos": 0.225,
            "compound": 0.4404
        },
        "vader_score_steemed": {
            "neg": 0.0,
            "neu": 0.775,
            "pos": 0.225,
            "compound": 0.4404
        },
        "vader_score_stopwords": {
            "neg": 0.0,
            "neu": 0.734,
            "pos": 0.266,
            "compound": 0.4404
        },
        "stock_ratio": {
            "-7": -0.0057664559372914625,
            "-5": 0.03415891137783914,
            "-3": 0.008002937609072785,
            "0": -0.04283941584555245,
            "3": -0.052178917572579545,
            "5": 0.007078996406692471,
            "7": -0.029435604201095825
        }
    },
    {
        "title": "NVIDIA Sets AI Inference Records, Introduces A30 and A10 GPUs for Enterprise Servers",
        "publish_date": "04/21/2021",
        "vader_score_raw": {
            "neg": 0.0,
            "neu": 1.0,
            "pos": 0.0,
            "compound": 0.0
        },
        "vader_score_lemmatized": {
            "neg": 0.0,
            "neu": 1.0,
            "pos": 0.0,
            "compound": 0.0
        },
        "vader_score_steemed": {
            "neg": 0.0,
            "neu": 1.0,
            "pos": 0.0,
            "compound": 0.0
        },
        "vader_score_stopwords": {
            "neg": 0.0,
            "neu": 1.0,
            "pos": 0.0,
            "compound": 0.0
        },
        "stock_ratio": {
            "-7": 0.03937807139856661,
            "-5": 0.04166418162262902,
            "-3": -0.004118906286684859,
            "0": -0.01263778779714873,
            "3": 0.008812784814893858,
            "5": 0.008812784814893858,
            "7": 0.0014375273693226771
        }
    },
    {
        "title": "Arm CEO says Nvidia merger better than going public",
        "publish_date": "07/02/2021",
        "vader_score_raw": {
            "neg": 0.0,
            "neu": 0.734,
            "pos": 0.266,
            "compound": 0.4404
        },
        "vader_score_lemmatized": {
            "neg": 0.0,
            "neu": 0.734,
            "pos": 0.266,
            "compound": 0.4404
        },
        "vader_score_steemed": {
            "neg": 0.0,
            "neu": 0.734,
            "pos": 0.266,
            "compound": 0.4404
        },
        "vader_score_stopwords": {
            "neg": 0.0,
            "neu": 0.707,
            "pos": 0.293,
            "compound": 0.4404
        },
        "stock_ratio": {
            "-7": 0.00995606657369871,
            "-5": 0.05001456192889713,
            "-3": 0.04135920167337267,
            "0": 0.03209251814680589,
            "3": 0.03166231661983631,
            "5": 0.005774713998431401,
            "7": -0.009687668453598539
        }
    },
    {
        "title": "Nvidia sets 4-for-1 stock split, shares rise",
        "publish_date": "05/21/2021",
        "vader_score_raw": {
            "neg": 0.0,
            "neu": 0.732,
            "pos": 0.268,
            "compound": 0.296
        },
        "vader_score_lemmatized": {
            "neg": 0.0,
            "neu": 0.732,
            "pos": 0.268,
            "compound": 0.296
        },
        "vader_score_steemed": {
            "neg": 0.0,
            "neu": 0.732,
            "pos": 0.268,
            "compound": 0.296
        },
        "vader_score_stopwords": {
            "neg": 0.0,
            "neu": 0.732,
            "pos": 0.268,
            "compound": 0.296
        },
        "stock_ratio": {
            "-7": 0.0012755175080110457,
            "-5": -0.0005845211982842005,
            "-3": -0.0031470087434546947,
            "0": 0.05195221872196339,
            "3": 0.07450627261251522,
            "5": 0.050212507639225475,
            "7": 0.050001719264102934
        }
    },
    {
        "title": "NVIDIA (NVDA) Spikes 5.6% on Upbeat Q1 Revenue Forecast",
        "publish_date": "04/30/2021",
        "vader_score_raw": {
            "neg": 0.0,
            "neu": 1.0,
            "pos": 0.0,
            "compound": 0.0
        },
        "vader_score_lemmatized": {
            "neg": 0.0,
            "neu": 1.0,
            "pos": 0.0,
            "compound": 0.0
        },
        "vader_score_steemed": {
            "neg": 0.0,
            "neu": 1.0,
            "pos": 0.0,
            "compound": 0.0
        },
        "vader_score_stopwords": {
            "neg": 0.0,
            "neu": 1.0,
            "pos": 0.0,
            "compound": 0.0
        },
        "stock_ratio": {
            "-7": -0.011123554237501797,
            "-5": 0.008812784814893858,
            "-3": 0.007518537261061229,
            "0": -0.014258462510184639,
            "3": -0.025480216071233984,
            "5": -0.03277682839121126,
            "7": 0.0035787943006682344
        }
    },
    {
        "title": "EU regulators pause investigation into Nvidia, ARM deal",
        "publish_date": "12/06/2021",
        "vader_score_raw": {
            "neg": 0.0,
            "neu": 1.0,
            "pos": 0.0,
            "compound": 0.0
        },
        "vader_score_lemmatized": {
            "neg": 0.0,
            "neu": 1.0,
            "pos": 0.0,
            "compound": 0.0
        },
        "vader_score_steemed": {
            "neg": 0.0,
            "neu": 1.0,
            "pos": 0.0,
            "compound": 0.0
        },
        "vader_score_stopwords": {
            "neg": 0.0,
            "neu": 1.0,
            "pos": 0.0,
            "compound": 0.0
        },
        "stock_ratio": {
            "-7": 0.03415891137783914,
            "-5": -0.023507608312560317,
            "-3": -0.04283941584555245,
            "0": -0.052178917572579545,
            "3": -0.02558521244834392,
            "5": -0.0781221551372784,
            "7": -0.0781221551372784
        }
    },
    {
        "title": "Leaked NVIDIA Hash Rate for Upcoming GPU Sparks Mining Questions",
        "publish_date": "04/23/2021",
        "vader_score_raw": {
            "neg": 0.204,
            "neu": 0.796,
            "pos": 0.0,
            "compound": -0.3182
        },
        "vader_score_lemmatized": {
            "neg": 0.204,
            "neu": 0.796,
            "pos": 0.0,
            "compound": -0.3182
        },
        "vader_score_steemed": {
            "neg": 0.195,
            "neu": 0.65,
            "pos": 0.154,
            "compound": -0.128
        },
        "vader_score_stopwords": {
            "neg": 0.223,
            "neu": 0.777,
            "pos": 0.0,
            "compound": -0.3182
        },
        "stock_ratio": {
            "-7": 0.04166418162262902,
            "-5": -0.004118906286684859,
            "-3": -0.023443998649194636,
            "0": -0.011123554237501797,
            "3": 0.008812784814893858,
            "5": 0.0014375273693226771,
            "7": -0.014258462510184639
        }
    },
    {
        "title": "NVIDIA's Shield TV Pro streamer drops back to $180",
        "publish_date": "12/13/2021",
        "vader_score_raw": {
            "neg": 0.0,
            "neu": 1.0,
            "pos": 0.0,
            "compound": 0.0
        },
        "vader_score_lemmatized": {
            "neg": 0.208,
            "neu": 0.792,
            "pos": 0.0,
            "compound": -0.2732
        },
        "vader_score_steemed": {
            "neg": 0.208,
            "neu": 0.792,
            "pos": 0.0,
            "compound": -0.2732
        },
        "vader_score_stopwords": {
            "neg": 0.0,
            "neu": 1.0,
            "pos": 0.0,
            "compound": 0.0
        },
        "stock_ratio": {
            "-7": -0.052178917572579545,
            "-5": 0.007078996406692471,
            "-3": -0.029435604201095825,
            "0": -0.0781221551372784,
            "3": -0.04401557918420446,
            "5": -0.03495946407116769,
            "7": -0.03495946407116769
        }
    },
    {
        "title": "The latest version of NVIDIA's DLSS technology is better at rendering moving objects",
        "publish_date": "11/16/2021",
        "vader_score_raw": {
            "neg": 0.0,
            "neu": 0.805,
            "pos": 0.195,
            "compound": 0.4404
        },
        "vader_score_lemmatized": {
            "neg": 0.0,
            "neu": 0.805,
            "pos": 0.195,
            "compound": 0.4404
        },
        "vader_score_steemed": {
            "neg": 0.0,
            "neu": 0.805,
            "pos": 0.195,
            "compound": 0.4404
        },
        "vader_score_stopwords": {
            "neg": 0.0,
            "neu": 0.734,
            "pos": 0.266,
            "compound": 0.4404
        },
        "stock_ratio": {
            "-7": 0.07385415408532073,
            "-5": 0.025397612303635398,
            "-3": -0.006156711737484063,
            "0": -0.0023924053182937605,
            "3": 0.07428497270466601,
            "5": 0.03324331192395766,
            "7": 0.020064198409553487
        }
    },
    {
        "title": "Nvidia's rally turbo charged by 'metaverse', valuation breaches $800 bln",
        "publish_date": "11/18/2021",
        "vader_score_raw": {
            "neg": 0.167,
            "neu": 0.833,
            "pos": 0.0,
            "compound": -0.2023
        },
        "vader_score_lemmatized": {
            "neg": 0.167,
            "neu": 0.833,
            "pos": 0.0,
            "compound": -0.2023
        },
        "vader_score_steemed": {
            "neg": 0.0,
            "neu": 1.0,
            "pos": 0.0,
            "compound": 0.0
        },
        "vader_score_stopwords": {
            "neg": 0.184,
            "neu": 0.816,
            "pos": 0.0,
            "compound": -0.2023
        },
        "stock_ratio": {
            "-7": 0.025397612303635398,
            "-5": -0.006156711737484063,
            "-3": -0.006156711737484063,
            "0": 0.04882623692017035,
            "3": 0.03324331192395766,
            "5": 0.020064198409553487,
            "7": -0.0057664559372914625
        }
    },
    {
        "title": "Here's How Long It Took Nvidia To Reach A $100B Market Cap",
        "publish_date": "05/21/2020",
        "vader_score_raw": {
            "neg": 0.0,
            "neu": 0.909,
            "pos": 0.091,
            "compound": 0.0258
        },
        "vader_score_lemmatized": {
            "neg": 0.0,
            "neu": 0.909,
            "pos": 0.091,
            "compound": 0.0258
        },
        "vader_score_steemed": {
            "neg": 0.0,
            "neu": 0.909,
            "pos": 0.091,
            "compound": 0.0258
        },
        "vader_score_stopwords": {
            "neg": 0.0,
            "neu": 0.864,
            "pos": 0.136,
            "compound": 0.0258
        },
        "stock_ratio": {
            "-7": 0.030353296338546314,
            "-5": 0.07966849083341229,
            "-3": 0.07966849083341229,
            "0": 0.03061141922757058,
            "3": -0.008312305060340652,
            "5": -0.008312305060340652,
            "7": -0.030958862975279472
        }
    },
    {
        "title": "Nvidia eclipses Intel as most valuable U.S. chipmaker",
        "publish_date": "07/08/2020",
        "vader_score_raw": {
            "neg": 0.0,
            "neu": 0.674,
            "pos": 0.326,
            "compound": 0.5256
        },
        "vader_score_lemmatized": {
            "neg": 0.0,
            "neu": 0.674,
            "pos": 0.326,
            "compound": 0.5256
        },
        "vader_score_steemed": {
            "neg": 0.0,
            "neu": 1.0,
            "pos": 0.0,
            "compound": 0.0
        },
        "vader_score_stopwords": {
            "neg": 0.0,
            "neu": 0.617,
            "pos": 0.383,
            "compound": 0.4767
        },
        "stock_ratio": {
            "-7": 0.017568366265262883,
            "-5": 0.03845510950587786,
            "-3": 0.03845510950587786,
            "0": 0.055262967817473724,
            "3": -0.003032068187232759,
            "5": -0.003032068187232759,
            "7": -0.001976082429648118
        }
    },
    {
        "title": "Is Nvidia the Best Blockchain Stock?",
        "publish_date": "11/25/2020",
        "vader_score_raw": {
            "neg": 0.0,
            "neu": 0.543,
            "pos": 0.457,
            "compound": 0.6369
        },
        "vader_score_lemmatized": {
            "neg": 0.0,
            "neu": 0.543,
            "pos": 0.457,
            "compound": 0.6369
        },
        "vader_score_steemed": {
            "neg": 0.0,
            "neu": 0.543,
            "pos": 0.457,
            "compound": 0.6369
        },
        "vader_score_stopwords": {
            "neg": 0.0,
            "neu": 0.417,
            "pos": 0.583,
            "compound": 0.6369
        },
        "stock_ratio": {
            "-7": 0.007429840741328566,
            "-5": -0.021716955417000604,
            "-3": -0.014477943383605127,
            "0": -0.0007362951867409737,
            "3": 0.013912727751747359,
            "5": 0.013912727751747359,
            "7": 0.020249031482144856
        }
    },
    {
        "title": "Nvidia follows Intel to predict strong growth in data center business",
        "publish_date": "11/14/2019",
        "vader_score_raw": {
            "neg": 0.0,
            "neu": 0.604,
            "pos": 0.396,
            "compound": 0.7096
        },
        "vader_score_lemmatized": {
            "neg": 0.0,
            "neu": 0.604,
            "pos": 0.396,
            "compound": 0.7096
        },
        "vader_score_steemed": {
            "neg": 0.0,
            "neu": 0.604,
            "pos": 0.396,
            "compound": 0.7096
        },
        "vader_score_stopwords": {
            "neg": 0.0,
            "neu": 0.543,
            "pos": 0.457,
            "compound": 0.7096
        },
        "stock_ratio": {
            "-7": 0.010875632355446923,
            "-5": 0.001808059167595784,
            "-3": 0.001808059167595784,
            "0": 0.005911402439626817,
            "3": 0.017502072095629463,
            "5": -0.003204043908142893,
            "7": 0.00483539093142338
        }
    },
    {
        "title": "Nvidia Signals That Growth of Data Center Business Will Slow",
        "publish_date": "08/19/2020",
        "vader_score_raw": {
            "neg": 0.0,
            "neu": 0.776,
            "pos": 0.224,
            "compound": 0.3818
        },
        "vader_score_lemmatized": {
            "neg": 0.0,
            "neu": 0.776,
            "pos": 0.224,
            "compound": 0.3818
        },
        "vader_score_steemed": {
            "neg": 0.0,
            "neu": 0.776,
            "pos": 0.224,
            "compound": 0.3818
        },
        "vader_score_stopwords": {
            "neg": 0.0,
            "neu": 0.698,
            "pos": 0.302,
            "compound": 0.3818
        },
        "stock_ratio": {
            "-7": 0.020087929409567273,
            "-5": 0.024693933973923575,
            "-3": 0.07950435308669512,
            "0": 0.03579026117373639,
            "3": 0.03723862405461135,
            "5": 0.03723862405461135,
            "7": 0.022225576090686698
        }
    },
    {
        "title": "Nvidia Valuation Soars Past Intel on Graphics Chip Boom",
        "publish_date": "07/08/2020",
        "vader_score_raw": {
            "neg": 0.0,
            "neu": 1.0,
            "pos": 0.0,
            "compound": 0.0
        },
        "vader_score_lemmatized": {
            "neg": 0.0,
            "neu": 1.0,
            "pos": 0.0,
            "compound": 0.0
        },
        "vader_score_steemed": {
            "neg": 0.0,
            "neu": 1.0,
            "pos": 0.0,
            "compound": 0.0
        },
        "vader_score_stopwords": {
            "neg": 0.0,
            "neu": 1.0,
            "pos": 0.0,
            "compound": 0.0
        },
        "stock_ratio": {
            "-7": 0.017568366265262883,
            "-5": 0.03845510950587786,
            "-3": 0.03845510950587786,
            "0": 0.055262967817473724,
            "3": -0.003032068187232759,
            "5": -0.003032068187232759,
            "7": -0.001976082429648118
        }
    },
    {
        "title": "Nvidia Accused of Trying to Discredit Ex-Employee in Crypto Mining Revenue Trial",
        "publish_date": "08/17/2020",
        "vader_score_raw": {
            "neg": 0.167,
            "neu": 0.833,
            "pos": 0.0,
            "compound": -0.296
        },
        "vader_score_lemmatized": {
            "neg": 0.167,
            "neu": 0.833,
            "pos": 0.0,
            "compound": -0.296
        },
        "vader_score_steemed": {
            "neg": 0.0,
            "neu": 1.0,
            "pos": 0.0,
            "compound": 0.0
        },
        "vader_score_stopwords": {
            "neg": 0.216,
            "neu": 0.784,
            "pos": 0.0,
            "compound": -0.296
        },
        "stock_ratio": {
            "-7": 0.004053170045849828,
            "-5": 0.020087929409567273,
            "-3": 0.024693933973923575,
            "0": 0.07950435308669512,
            "3": 0.019952136313557793,
            "5": 0.03723862405461135,
            "7": 0.03723862405461135
        }
    },
    {
        "title": "How Does NVIDIA's (NASDAQ:NVDA) P/E Compare To Its Industry, After The Share Price Drop?\n",
        "publish_date": "03/17/2020",
        "vader_score_raw": {
            "neg": 0.129,
            "neu": 0.736,
            "pos": 0.135,
            "compound": 0.0258
        },
        "vader_score_lemmatized": {
            "neg": 0.129,
            "neu": 0.736,
            "pos": 0.135,
            "compound": 0.0258
        },
        "vader_score_steemed": {
            "neg": 0.129,
            "neu": 0.736,
            "pos": 0.135,
            "compound": 0.0258
        },
        "vader_score_stopwords": {
            "neg": 0.204,
            "neu": 0.583,
            "pos": 0.214,
            "compound": 0.0258
        },
        "stock_ratio": {
            "-7": -0.024093889612766956,
            "-5": -0.15557622061887288,
            "-3": -0.17803640094170328,
            "0": -0.06338170140676279,
            "3": -0.03491774643560675,
            "5": 6.053285321639624e-05,
            "7": 0.16510809364694035
        }
    },
    {
        "title": "Nvidia Poised for Record Sales as AI Demand Kicks In",
        "publish_date": "05/25/2023",
        "vader_score_raw": {
            "neg": 0.13,
            "neu": 0.696,
            "pos": 0.174,
            "compound": 0.128
        },
        "vader_score_lemmatized": {
            "neg": 0.13,
            "neu": 0.696,
            "pos": 0.174,
            "compound": 0.128
        },
        "vader_score_steemed": {
            "neg": 0.143,
            "neu": 0.857,
            "pos": 0.0,
            "compound": -0.128
        },
        "vader_score_stopwords": {
            "neg": 0.176,
            "neu": 0.588,
            "pos": 0.235,
            "compound": 0.128
        },
        "stock_ratio": {
            "-7": 0.07735210727135826,
            "-5": 0.035246402822800345,
            "-3": 0.035246402822800345,
            "0": 0.18951946960981553,
            "3": 0.1664872555096856,
            "5": 0.1664872555096856,
            "7": 0.08802630782663767
        }
    },
    {
        "title": "Nvidia Stock\u2019s Surge Makes Chip Maker 10th-Biggest U.S. Listed Company",
        "publish_date": "07/19/2021",
        "vader_score_raw": {
            "neg": 0.0,
            "neu": 1.0,
            "pos": 0.0,
            "compound": 0.0
        },
        "vader_score_lemmatized": {
            "neg": 0.0,
            "neu": 1.0,
            "pos": 0.0,
            "compound": 0.0
        },
        "vader_score_steemed": {
            "neg": 0.0,
            "neu": 1.0,
            "pos": 0.0,
            "compound": 0.0
        },
        "vader_score_stopwords": {
            "neg": 0.0,
            "neu": 1.0,
            "pos": 0.0,
            "compound": 0.0
        },
        "stock_ratio": {
            "-7": 0.009510647468803528,
            "-5": -0.019323540858203994,
            "-3": -0.07667728196526039,
            "0": -0.03736782658545842,
            "3": 0.02844463908469955,
            "5": 0.01236227650454569,
            "7": 0.01236227650454569
        }
    },
    {
        "title": "Nvidia Posts Record Revenue as Videogaming Sales Soar",
        "publish_date": "11/17/2021",
        "vader_score_raw": {
            "neg": 0.0,
            "neu": 1.0,
            "pos": 0.0,
            "compound": 0.0
        },
        "vader_score_lemmatized": {
            "neg": 0.0,
            "neu": 1.0,
            "pos": 0.0,
            "compound": 0.0
        },
        "vader_score_steemed": {
            "neg": 0.0,
            "neu": 1.0,
            "pos": 0.0,
            "compound": 0.0
        },
        "vader_score_stopwords": {
            "neg": 0.0,
            "neu": 1.0,
            "pos": 0.0,
            "compound": 0.0
        },
        "stock_ratio": {
            "-7": 0.013471038025234645,
            "-5": 0.006991658784402685,
            "-3": -0.006156711737484063,
            "0": -0.02641840486398721,
            "3": 0.03324331192395766,
            "5": 0.03324331192395766,
            "7": 0.03726989143153657
        }
    },
    {
        "title": "Nvidia Posts Record Sales as Pandemic Sustains Demand for Gaming, Data-Center Chips",
        "publish_date": "08/19/2020",
        "vader_score_raw": {
            "neg": 0.12,
            "neu": 0.88,
            "pos": 0.0,
            "compound": -0.128
        },
        "vader_score_lemmatized": {
            "neg": 0.12,
            "neu": 0.88,
            "pos": 0.0,
            "compound": -0.128
        },
        "vader_score_steemed": {
            "neg": 0.12,
            "neu": 0.88,
            "pos": 0.0,
            "compound": -0.128
        },
        "vader_score_stopwords": {
            "neg": 0.143,
            "neu": 0.857,
            "pos": 0.0,
            "compound": -0.128
        },
        "stock_ratio": {
            "-7": 0.020087929409567273,
            "-5": 0.024693933973923575,
            "-3": 0.07950435308669512,
            "0": 0.03579026117373639,
            "3": 0.03723862405461135,
            "5": 0.03723862405461135,
            "7": 0.022225576090686698
        }
    },
    {
        "title": "How Nvidia\u2019s CEO Cooked Up America\u2019s Biggest Semiconductor Company",
        "publish_date": "09/15/2020",
        "vader_score_raw": {
            "neg": 0.0,
            "neu": 1.0,
            "pos": 0.0,
            "compound": 0.0
        },
        "vader_score_lemmatized": {
            "neg": 0.0,
            "neu": 1.0,
            "pos": 0.0,
            "compound": 0.0
        },
        "vader_score_steemed": {
            "neg": 0.0,
            "neu": 1.0,
            "pos": 0.0,
            "compound": 0.0
        },
        "vader_score_stopwords": {
            "neg": 0.0,
            "neu": 1.0,
            "pos": 0.0,
            "compound": 0.0
        },
        "stock_ratio": {
            "-7": -0.09586411475526313,
            "-5": -0.05028362059012269,
            "-3": 0.028434277017658473,
            "0": 0.0382120930023482,
            "3": -0.024935248104831945,
            "5": -0.0010432242635960856,
            "7": 0.0031609681130485238
        }
    }
]